larapy_installer/__init__.py
larapy_installer/src/__init__.py
larapy_installer/src/Command/NewCommand.py
larapy_installer/src/Command/__init__.py
larapy_installer-0.4.2.data/scripts/larapy
larapy_installer-0.4.2.dist-info/METADATA
larapy_installer-0.4.2.dist-info/WHEEL
larapy_installer-0.4.2.dist-info/top_level.txt
larapy_installer-0.4.2.dist-info/RECORD
