Metadata-Version: 2.1
Name: larapy-installer
Version: 0.4.2
Summary: Larapy installer for crafting larapy application.
Home-page: https://github.com/LaravelPython/installer
Author: Bedram Tamang
Author-email: tmgbedu@gmail.com
License: UNKNOWN
Platform: UNKNOWN
Classifier: Programming Language :: Python :: 3
Classifier: License :: OSI Approved :: MIT License
Classifier: Operating System :: OS Independent
Requires-Dist: cleo
Requires-Dist: requests
